elasticsearch_interface/__init__.py
elasticsearch_interface/es.py
elasticsearch_interface/utils.py
elasticsearch_interface-1.5.0.dist-info/licenses/LICENSE
elasticsearch_interface-1.5.0.dist-info/METADATA
elasticsearch_interface-1.5.0.dist-info/WHEEL
elasticsearch_interface-1.5.0.dist-info/top_level.txt
elasticsearch_interface-1.5.0.dist-info/RECORD
