Metadata-Version: 2.4
Name: elasticsearch-interface
Version: 1.5.0
Summary: Interface to interact with elasticsearch's python client for the use case of EPFL Graph
Author-email: Aitor Pérez <aitor.perez@epfl.ch>, Ramtin Yazdanian <ramtin.yazdanian@epfl.ch>
Project-URL: Homepage, https://github.com/epflgraph/elasticsearch-interface
Project-URL: Source code, https://github.com/epflgraph/elasticsearch-interface
Project-URL: Documentation, https://github.com/epflgraph/elasticsearch-interface
Project-URL: Bug Tracker, https://github.com/epflgraph/elasticsearch-interface/issues
Classifier: Programming Language :: Python :: 3
Classifier: Operating System :: OS Independent
Requires-Python: >=3.7
License-File: LICENSE
Requires-Dist: elasticsearch
Dynamic: license-file
